evalSemanticSeg/__init__.py
evalSemanticSeg/cityscapes_label_data.py
evalSemanticSeg/cityscapes_labels.py
evalSemanticSeg/cvat_to_cityscape_labels.py
evalSemanticSeg/eval.py
evalSemanticSeg/evaluator.py
evalSemanticSeg/extract_labels.py
evalSemanticSeg-0.0.2.dist-info/LICENSE
evalSemanticSeg-0.0.2.dist-info/METADATA
evalSemanticSeg-0.0.2.dist-info/WHEEL
evalSemanticSeg-0.0.2.dist-info/top_level.txt
evalSemanticSeg-0.0.2.dist-info/RECORD
